[
  {
    "title":"AgroTwin",
    "creator": "Agrobit srl",
    "date": "21/06/2024",
    "icon":"https://raw.githubusercontent.com/ICAERUS-EU/AgroTwin/refs/heads/main/docs/images/Extracted_portion.png",
    "url":"https://github.com/ICAERUS-EU/AgroTwin",
    "icaerus_applications": ["crop-monitoring", "crop-spraying"],
    "uses_cases":["OCT"],
    "extra":{
        "usage/description": "A UAV-specific Python image processing library built upon scipy for a comprehensive analysis of vineyard point clouds to extract relevant features, and calculating descriptors such as canopy density, height, thickness, and optimal volume rate for spraying."
    },
    "filters":{
        "content": [
            "Machine learning",
            "Deep learning",
            "Point cloud",
            "VRT",
            "Vigor",
            "RGB",
            "Framework",
            "VLOS"
        ],  
        "data-type": [
            "RGB images",
            "Point cloud",
            "csv"
        ], 
        "subject": [
            "Vineyards"
        ],
        "location": [
            "Italy"
        ] 
    }
  },
  {  
    "title":"Xylella Fastidiosa Classification",
    "creator": "TAAL",
    "date": "01/08/2024",
    "icon":"https://taal.it/wp-content/uploads/2023/09/sensor-cropped.png",
    "url": "https://github.com/ICAERUS-EU/Xylella-Fastidiosa-Classification",
    "icaerus_applications": ["crop-monitoring"],
    "uses_cases":["OCT"],
    "extra":{
        "usage/description": "Training and validation of a classifier for Xylella Fastidiosa in olive trees."
    },
    "filters":{
        "content": [
            "Vegetation Index",
            "Orthomosaic processing toolbox"
            ],  
        "data-type": [
            "Multispectral images",
            "RGB images",
            "Orthomosaic"
        ], 
        "subject": [
            "Disease detection",
            "Olive groves"
        ],
        "location": [
            "Italy"
        ]
    }
  },
  {  
    "title":"Full Pipeline Olive Tree Health Status Classification",
    "creator": "TAAL",
    "date": "01/08/2024",
    "icon":"https://taal.it/wp-content/uploads/2023/09/sensor-cropped.png",
    "url": "https://github.com/ICAERUS-EU/Full-Pipeline-Olive-Tree-Health-Status-Classification",
    "icaerus_applications": ["crop-monitoring"],
    "uses_cases":["OCT"],
    "extra":{
        "usage/description": "An image processing workflow designed to classify olive trees by combining data from NDVI (Normalized Difference Vegetation Index) and RGB images."
    },
    "filters":{
        "content": [
            "Vegetation Index",
            "Orthomosaic processing toolbox"
        ],  
        "data-type": [
            "Multispectral images",
            "RGB images",
            "Orthomosaic"
        ], 
        "subject": [
            "Disease detection",
            "Olive groves"
        ],
        "location": [
            "Italy"
        ]
    }
  },
  {
    "title":"Olive Tree Detection",
    "creator": "TAAL",
    "date": "1/8/2024",
    "icon":"https://taal.it/wp-content/uploads/2023/09/sensor-cropped.png",
    "url": "https://github.com/ICAERUS-EU/Olive-Tree-Detection",
    "icaerus_applications": ["crop-monitoring"],
    "uses_cases":["OCT"],
    "extra":{
        "usage/description": "Training and validation of a detection model for olive trees using YOLO"
    },
    "filters":{
        "content": [
            "Vegetation Index",
            "Orthomosaic processing toolbox"
        ],  
        "data-type": [
            "Multispectral images",
            "RGB images",
            "Orthomosaic"
        ], 
        "subject": [
            "Disease detection",
            "Olive groves"
        ],
        "location": [
            "Italy"
        ]
    }
  }
]
